kagazkit/__init__.py
kagazkit/main.py
kagazkit/core/__init__.py
kagazkit/core/actions.py
kagazkit/core/validators.py
kagazkit/ui/__init__.py
kagazkit/ui/app.py
kagazkit/ui/components/__init__.py
kagazkit/ui/components/file_list.py
kagazkit/ui/pages/__init__.py
kagazkit/ui/pages/image_page.py
kagazkit/ui/pages/merge_page.py
kagazkit/ui/pages/tools_page.py
kagazkit-0.1.4.dist-info/licenses/LICENSE
kagazkit-0.1.4.dist-info/METADATA
kagazkit-0.1.4.dist-info/WHEEL
kagazkit-0.1.4.dist-info/entry_points.txt
kagazkit-0.1.4.dist-info/top_level.txt
kagazkit-0.1.4.dist-info/RECORD
