Metadata-Version: 2.4
Name: kagazkit
Version: 0.1.4
Summary: KagazKit - Your Ultimate PDF Toolkit. Merge, Split, Convert, and more.
Author: Farjad Hasan
License: MIT License
Project-URL: Homepage, https://github.com/farjad-hasan/kagazkit
Project-URL: Bug Tracker, https://github.com/farjad-hasan/kagazkit/issues
Project-URL: LinkedIn, https://www.linkedin.com/in/farjadh/
Project-URL: X, https://x.com/im_farjad
Classifier: Programming Language :: Python :: 3
Classifier: License :: OSI Approved :: MIT License
Classifier: Operating System :: OS Independent
Requires-Python: >=3.9
License-File: LICENSE
Requires-Dist: customtkinter==5.2.2
Requires-Dist: Pillow>=10.0.0
Requires-Dist: PyPDF2>=3.0.0
Requires-Dist: tkinterdnd2>=0.3.0
Requires-Dist: packaging>=23.0
Dynamic: license-file
